Metadata-Version: 2.1
Name: rskit
Version: 0.0.1
Summary: Toolkit for recommender systems
Home-page: https://github.com/micaleel/rskit
Author: Khalil Muhammad
Author-email: micaleel@gmail.com
License: MIT
Keywords: personalization,recommenders,recommender systems
Platform: UNKNOWN
Requires-Python: >=3
